soagen/__init__.py
soagen/column.py
soagen/config.py
soagen/configurable.py
soagen/cpp.py
soagen/errors.py
soagen/header_file.py
soagen/includes.py
soagen/injectors.py
soagen/log.py
soagen/main.py
soagen/metavars.py
soagen/natvis_file.py
soagen/paths.py
soagen/preprocessor.py
soagen/schemas.py
soagen/struct.py
soagen/type_list.py
soagen/utils.py
soagen/variable.py
soagen/version.py
soagen/version.txt
soagen/writer.py
soagen/hpp/.clang-format
soagen/hpp/allocator.hpp
soagen/hpp/column_traits.hpp
soagen/hpp/core.hpp
soagen/hpp/emplacer.hpp
soagen/hpp/for_each.hpp
soagen/hpp/header_end.hpp
soagen/hpp/header_start.hpp
soagen/hpp/invoke.hpp
soagen/hpp/iterator.hpp
soagen/hpp/names.hpp
soagen/hpp/row.hpp
soagen/hpp/soagen.hpp
soagen/hpp/span.hpp
soagen/hpp/table.hpp
soagen/hpp/table_traits.hpp
soagen/hpp/tuples.hpp
soagen/hpp/generated/compressed_pair.hpp
soagen/hpp/generated/functions.hpp
soagen/hpp/generated/preprocessor.hpp
soagen/hpp/generated/version.hpp
soagen/hpp/mixins/all.hpp
soagen/hpp/mixins/columns.hpp
soagen/hpp/mixins/data_ptr.hpp
soagen/hpp/mixins/equality_comparable.hpp
soagen/hpp/mixins/iterators.hpp
soagen/hpp/mixins/less_than_comparable.hpp
soagen/hpp/mixins/resizable.hpp
soagen/hpp/mixins/rows.hpp
soagen/hpp/mixins/size_and_capacity.hpp
soagen/hpp/mixins/spans.hpp
soagen/hpp/mixins/swappable.hpp
soagen/hpp/single/.clang-format
soagen/hpp/single/soagen.hpp
soagen-0.7.0.dist-info/LICENSE.txt
soagen-0.7.0.dist-info/METADATA
soagen-0.7.0.dist-info/WHEEL
soagen-0.7.0.dist-info/entry_points.txt
soagen-0.7.0.dist-info/top_level.txt
soagen-0.7.0.dist-info/zip-safe
soagen-0.7.0.dist-info/RECORD
