Metadata-Version: 2.1
Name: soagen
Version: 0.7.0
Summary: Struct-of-Arrays for C++.
Author-email: Mark Gillard <mark.gillard@outlook.com.au>
License: MIT
Project-URL: Source, https://github.com/marzer/soagen
Project-URL: Tracker, https://github.com/marzer/soagen/issues
Project-URL: Funding, https://github.com/sponsors/marzer
Keywords: c++,soa,struct-of-arrays,structure-of-arrays,struct of arrays,structure of arrays,parallel-arrays,parallel arrays,std::vector
Classifier: Development Status :: 3 - Alpha
Classifier: License :: OSI Approved :: MIT License
Classifier: Programming Language :: C++
Classifier: Topic :: Software Development :: Code Generators
Classifier: Topic :: Utilities
Requires-Python: >=3.9
License-File: LICENSE.txt
Requires-Dist: misk >=0.8.1
Requires-Dist: tomli
Requires-Dist: schema !=0.7.5
Requires-Dist: colorama
Requires-Dist: trieregex
